Wkwmd/ybbmiTest.py
ybbmiTest-0.0.0.1.dist-info/METADATA
ybbmiTest-0.0.0.1.dist-info/WHEEL
ybbmiTest-0.0.0.1.dist-info/top_level.txt
ybbmiTest-0.0.0.1.dist-info/RECORD
