Metadata-Version: 2.1
Name: ybbmiTest
Version: 0.0.0.1
Summary: My 2nd Test Package
Home-page: https://www.naver.com
Author: Youngbum Gim
Author-email: znslek@gmail.com
License: MIT
Platform: UNKNOWN
Requires-Python: >=3
